jpx_derivatives/__init__.py
jpx_derivatives/bsm.py
jpx_derivatives/check_maturity.py
jpx_derivatives/client.py
jpx_derivatives/config.py
jpx_derivatives/get_interest_rate_torf.py
jpx_derivatives/holidays.py
jpx_derivatives/sq.py
jpx_derivatives/symbolcode_futures.py
jpx_derivatives/trading_session.py
jpx_derivatives-0.1.0.dev7.dist-info/METADATA
jpx_derivatives-0.1.0.dev7.dist-info/WHEEL
jpx_derivatives-0.1.0.dev7.dist-info/licenses/LICENSE
jpx_derivatives-0.1.0.dev7.dist-info/RECORD
