Metadata-Version: 2.4
Name: jpx-derivatives
Version: 0.1.0.dev7
Summary: JPX Derivatives Data Management
License-File: LICENSE
Requires-Python: >=3.12
Requires-Dist: duckdb>=1.1.3
Requires-Dist: lxml>=5.3.0
Requires-Dist: numpy>=2.2.2
Requires-Dist: openpyxl>=3.1.5
Requires-Dist: pandas>=2.2.3
Requires-Dist: pyarrow>=2.32.3
Requires-Dist: pytest-playwright>=0.7.0
Requires-Dist: requests
Requires-Dist: scipy>=1.15.1
